mapquest/__init__.py
mapquest/endpointdata.py
mapquest/mapquestapiprocessor.py
mapquest/mapquestclient.py
mapquest/mapquestendpoints.py
mapquest-0.0.1.dist-info/LICENSE
mapquest-0.0.1.dist-info/METADATA
mapquest-0.0.1.dist-info/WHEEL
mapquest-0.0.1.dist-info/top_level.txt
mapquest-0.0.1.dist-info/RECORD
